{"song": "Data/songs/edge.mp3", "tilemap": {"5;17": {"type": "stone", "variant": 1, "pos": [5, 17], "size": "t"}, "6;17": {"type": "stone", "variant": 1, "pos": [6, 17], "size": "t"}, "7;17": {"type": "stone", "variant": 1, "pos": [7, 17], "size": "t"}, "8;17": {"type": "stone", "variant": 1, "pos": [8, 17], "size": "t"}, "9;17": {"type": "stone", "variant": 1, "pos": [9, 17], "size": "t"}, "10;17": {"type": "stone", "variant": 1, "pos": [10, 17], "size": "t"}, "11;17": {"type": "stone", "variant": 1, "pos": [11, 17], "size": "t"}, "12;17": {"type": "stone", "variant": 1, "pos": [12, 17], "size": "t"}, "13;17": {"type": "stone", "variant": 1, "pos": [13, 17], "size": "t"}, "14;17": {"type": "stone", "variant": 1, "pos": [14, 17], "size": "t"}, "15;17": {"type": "stone", "variant": 1, "pos": [15, 17], "size": "t"}, "16;17": {"type": "stone", "variant": 1, "pos": [16, 17], "size": "t"}, "17;17": {"type": "stone", "variant": 1, "pos": [17, 17], "size": "t"}, "18;17": {"type": "stone", "variant": 1, "pos": [18, 17], "size": "t"}, "19;17": {"type": "stone", "variant": 1, "pos": [19, 17], "size": "t"}, "20;17": {"type": "stone", "variant": 1, "pos": [20, 17], "size": "t"}, "21;17": {"type": "stone", "variant": 1, "pos": [21, 17], "size": "t"}, "22;17": {"type": "stone", "variant": 1, "pos": [22, 17], "size": "t"}, "23;17": {"type": "stone", "variant": 1, "pos": [23, 17], "size": "t"}, "24;17": {"type": "stone", "variant": 1, "pos": [24, 17], "size": "t"}, "25;17": {"type": "stone", "variant": 1, "pos": [25, 17], "size": "t"}, "26;17": {"type": "stone", "variant": 1, "pos": [26, 17], "size": "t"}, "27;17": {"type": "stone", "variant": 1, "pos": [27, 17], "size": "t"}, "28;17": {"type": "stone", "variant": 1, "pos": [28, 17], "size": "t"}, "29;17": {"type": "stone", "variant": 1, "pos": [29, 17], "size": "t"}, "30;17": {"type": "stone", "variant": 1, "pos": [30, 17], "size": "t"}, "31;17": {"type": "stone", "variant": 1, "pos": [31, 17], "size": "t"}, "32;17": {"type": "stone", "variant": 1, "pos": [32, 17], "size": "t"}, "33;17": {"type": "stone", "variant": 1, "pos": [33, 17], "size": "t"}, "34;17": {"type": "stone", "variant": 1, "pos": [34, 17], "size": "t"}, "35;17": {"type": "stone", "variant": 8, "pos": [35, 17], "size": "t"}, "36;17": {"type": "stone", "variant": 3, "pos": [36, 17], "size": "t"}, "25;18": {"type": "stone", "variant": 8, "pos": [25, 18], "size": "t"}, "24;18": {"type": "stone", "variant": 8, "pos": [24, 18], "size": "t"}, "22;18": {"type": "stone", "variant": 8, "pos": [22, 18], "size": "t"}, "20;18": {"type": "stone", "variant": 8, "pos": [20, 18], "size": "t"}, "19;18": {"type": "stone", "variant": 8, "pos": [19, 18], "size": "t"}, "18;18": {"type": "stone", "variant": 8, "pos": [18, 18], "size": "t"}, "17;18": {"type": "stone", "variant": 8, "pos": [17, 18], "size": "t"}, "16;18": {"type": "stone", "variant": 8, "pos": [16, 18], "size": "t"}, "15;18": {"type": "stone", "variant": 8, "pos": [15, 18], "size": "t"}, "14;18": {"type": "stone", "variant": 8, "pos": [14, 18], "size": "t"}, "13;18": {"type": "stone", "variant": 8, "pos": [13, 18], "size": "t"}, "12;18": {"type": "stone", "variant": 8, "pos": [12, 18], "size": "t"}, "11;18": {"type": "stone", "variant": 8, "pos": [11, 18], "size": "t"}, "10;18": {"type": "stone", "variant": 8, "pos": [10, 18], "size": "t"}, "9;18": {"type": "stone", "variant": 8, "pos": [9, 18], "size": "t"}, "8;18": {"type": "stone", "variant": 8, "pos": [8, 18], "size": "t"}, "4;17": {"type": "stone", "variant": 1, "pos": [4, 17], "size": "t"}, "3;17": {"type": "stone", "variant": 8, "pos": [3, 17], "size": "t"}, "2;17": {"type": "stone", "variant": 7, "pos": [2, 17], "size": "t"}, "2;18": {"type": "stone", "variant": 6, "pos": [2, 18], "size": "t"}, "3;18": {"type": "stone", "variant": 8, "pos": [3, 18], "size": "t"}, "4;18": {"type": "stone", "variant": 8, "pos": [4, 18], "size": "t"}, "5;18": {"type": "stone", "variant": 8, "pos": [5, 18], "size": "t"}, "6;18": {"type": "stone", "variant": 8, "pos": [6, 18], "size": "t"}, "7;18": {"type": "stone", "variant": 8, "pos": [7, 18], "size": "t"}, "21;18": {"type": "stone", "variant": 8, "pos": [21, 18], "size": "t"}, "23;18": {"type": "stone", "variant": 8, "pos": [23, 18], "size": "t"}, "26;18": {"type": "stone", "variant": 8, "pos": [26, 18], "size": "t"}, "27;18": {"type": "stone", "variant": 8, "pos": [27, 18], "size": "t"}, "28;18": {"type": "stone", "variant": 8, "pos": [28, 18], "size": "t"}, "29;18": {"type": "stone", "variant": 8, "pos": [29, 18], "size": "t"}, "30;18": {"type": "stone", "variant": 8, "pos": [30, 18], "size": "t"}, "31;18": {"type": "stone", "variant": 8, "pos": [31, 18], "size": "t"}, "32;18": {"type": "stone", "variant": 8, "pos": [32, 18], "size": "t"}, "33;18": {"type": "stone", "variant": 8, "pos": [33, 18], "size": "t"}, "34;18": {"type": "stone", "variant": 8, "pos": [34, 18], "size": "t"}, "35;18": {"type": "stone", "variant": 8, "pos": [35, 18], "size": "t"}, "36;18": {"type": "stone", "variant": 4, "pos": [36, 18], "size": "t"}, "35;19": {"type": "stone", "variant": 4, "pos": [35, 19], "size": "t"}, "34;19": {"type": "stone", "variant": 5, "pos": [34, 19], "size": "t"}, "33;19": {"type": "stone", "variant": 5, "pos": [33, 19], "size": "t"}, "32;19": {"type": "stone", "variant": 5, "pos": [32, 19], "size": "t"}, "31;19": {"type": "stone", "variant": 5, "pos": [31, 19], "size": "t"}, "30;19": {"type": "stone", "variant": 5, "pos": [30, 19], "size": "t"}, "29;19": {"type": "stone", "variant": 5, "pos": [29, 19], "size": "t"}, "28;19": {"type": "stone", "variant": 5, "pos": [28, 19], "size": "t"}, "27;19": {"type": "stone", "variant": 5, "pos": [27, 19], "size": "t"}, "26;19": {"type": "stone", "variant": 5, "pos": [26, 19], "size": "t"}, "25;19": {"type": "stone", "variant": 5, "pos": [25, 19], "size": "t"}, "24;19": {"type": "stone", "variant": 5, "pos": [24, 19], "size": "t"}, "23;19": {"type": "stone", "variant": 5, "pos": [23, 19], "size": "t"}, "22;19": {"type": "stone", "variant": 5, "pos": [22, 19], "size": "t"}, "21;19": {"type": "stone", "variant": 5, "pos": [21, 19], "size": "t"}, "20;19": {"type": "stone", "variant": 5, "pos": [20, 19], "size": "t"}, "19;19": {"type": "stone", "variant": 5, "pos": [19, 19], "size": "t"}, "18;19": {"type": "stone", "variant": 5, "pos": [18, 19], "size": "t"}, "17;19": {"type": "stone", "variant": 5, "pos": [17, 19], "size": "t"}, "16;19": {"type": "stone", "variant": 5, "pos": [16, 19], "size": "t"}, "15;19": {"type": "stone", "variant": 5, "pos": [15, 19], "size": "t"}, "14;19": {"type": "stone", "variant": 5, "pos": [14, 19], "size": "t"}, "13;19": {"type": "stone", "variant": 5, "pos": [13, 19], "size": "t"}, "12;19": {"type": "stone", "variant": 5, "pos": [12, 19], "size": "t"}, "11;19": {"type": "stone", "variant": 5, "pos": [11, 19], "size": "t"}, "10;19": {"type": "stone", "variant": 5, "pos": [10, 19], "size": "t"}, "9;19": {"type": "stone", "variant": 5, "pos": [9, 19], "size": "t"}, "8;19": {"type": "stone", "variant": 5, "pos": [8, 19], "size": "t"}, "7;19": {"type": "stone", "variant": 5, "pos": [7, 19], "size": "t"}, "6;19": {"type": "stone", "variant": 5, "pos": [6, 19], "size": "t"}, "5;19": {"type": "stone", "variant": 5, "pos": [5, 19], "size": "t"}, "4;19": {"type": "stone", "variant": 5, "pos": [4, 19], "size": "t"}, "3;19": {"type": "stone", "variant": 6, "pos": [3, 19], "size": "t"}, "2;16": {"type": "stone", "variant": 7, "pos": [2, 16], "size": "t"}, "2;15": {"type": "stone", "variant": 7, "pos": [2, 15], "size": "t"}, "2;14": {"type": "stone", "variant": 7, "pos": [2, 14], "size": "t"}, "2;13": {"type": "stone", "variant": 7, "pos": [2, 13], "size": "t"}, "2;12": {"type": "stone", "variant": 7, "pos": [2, 12], "size": "t"}, "2;11": {"type": "stone", "variant": 7, "pos": [2, 11], "size": "t"}, "2;10": {"type": "stone", "variant": 7, "pos": [2, 10], "size": "t"}, "2;9": {"type": "stone", "variant": 7, "pos": [2, 9], "size": "t"}, "2;8": {"type": "stone", "variant": 7, "pos": [2, 8], "size": "t"}, "2;7": {"type": "stone", "variant": 7, "pos": [2, 7], "size": "t"}, "2;6": {"type": "stone", "variant": 7, "pos": [2, 6], "size": "t"}, "2;5": {"type": "stone", "variant": 7, "pos": [2, 5], "size": "t"}, "3;5": {"type": "stone", "variant": 8, "pos": [3, 5], "size": "t"}, "4;5": {"type": "stone", "variant": 5, "pos": [4, 5], "size": "t"}, "3;6": {"type": "stone", "variant": 3, "pos": [3, 6], "size": "t"}, "3;7": {"type": "stone", "variant": 3, "pos": [3, 7], "size": "t"}, "3;8": {"type": "stone", "variant": 3, "pos": [3, 8], "size": "t"}, "3;9": {"type": "stone", "variant": 3, "pos": [3, 9], "size": "t"}, "3;10": {"type": "stone", "variant": 3, "pos": [3, 10], "size": "t"}, "3;11": {"type": "stone", "variant": 3, "pos": [3, 11], "size": "t"}, "3;12": {"type": "stone", "variant": 3, "pos": [3, 12], "size": "t"}, "3;13": {"type": "stone", "variant": 3, "pos": [3, 13], "size": "t"}, "3;14": {"type": "stone", "variant": 3, "pos": [3, 14], "size": "t"}, "3;15": {"type": "stone", "variant": 3, "pos": [3, 15], "size": "t"}, "3;16": {"type": "stone", "variant": 3, "pos": [3, 16], "size": "t"}, "35;16": {"type": "stone", "variant": 7, "pos": [35, 16], "size": "t"}, "35;15": {"type": "stone", "variant": 7, "pos": [35, 15], "size": "t"}, "35;14": {"type": "stone", "variant": 7, "pos": [35, 14], "size": "t"}, "35;13": {"type": "stone", "variant": 7, "pos": [35, 13], "size": "t"}, "35;12": {"type": "stone", "variant": 7, "pos": [35, 12], "size": "t"}, "35;11": {"type": "stone", "variant": 7, "pos": [35, 11], "size": "t"}, "35;10": {"type": "stone", "variant": 7, "pos": [35, 10], "size": "t"}, "35;9": {"type": "stone", "variant": 7, "pos": [35, 9], "size": "t"}, "35;8": {"type": "stone", "variant": 7, "pos": [35, 8], "size": "t"}, "35;7": {"type": "stone", "variant": 7, "pos": [35, 7], "size": "t"}, "35;6": {"type": "stone", "variant": 7, "pos": [35, 6], "size": "t"}, "35;5": {"type": "stone", "variant": 8, "pos": [35, 5], "size": "t"}, "5;5": {"type": "stone", "variant": 5, "pos": [5, 5], "size": "t"}, "6;5": {"type": "stone", "variant": 5, "pos": [6, 5], "size": "t"}, "7;5": {"type": "stone", "variant": 5, "pos": [7, 5], "size": "t"}, "8;5": {"type": "stone", "variant": 5, "pos": [8, 5], "size": "t"}, "9;5": {"type": "stone", "variant": 5, "pos": [9, 5], "size": "t"}, "10;5": {"type": "stone", "variant": 5, "pos": [10, 5], "size": "t"}, "11;5": {"type": "stone", "variant": 5, "pos": [11, 5], "size": "t"}, "12;5": {"type": "stone", "variant": 5, "pos": [12, 5], "size": "t"}, "13;5": {"type": "stone", "variant": 5, "pos": [13, 5], "size": "t"}, "14;5": {"type": "stone", "variant": 5, "pos": [14, 5], "size": "t"}, "15;5": {"type": "stone", "variant": 5, "pos": [15, 5], "size": "t"}, "16;5": {"type": "stone", "variant": 5, "pos": [16, 5], "size": "t"}, "17;5": {"type": "stone", "variant": 5, "pos": [17, 5], "size": "t"}, "18;5": {"type": "stone", "variant": 5, "pos": [18, 5], "size": "t"}, "19;5": {"type": "stone", "variant": 5, "pos": [19, 5], "size": "t"}, "20;5": {"type": "stone", "variant": 5, "pos": [20, 5], "size": "t"}, "21;5": {"type": "stone", "variant": 5, "pos": [21, 5], "size": "t"}, "22;5": {"type": "stone", "variant": 5, "pos": [22, 5], "size": "t"}, "23;5": {"type": "stone", "variant": 5, "pos": [23, 5], "size": "t"}, "24;5": {"type": "stone", "variant": 5, "pos": [24, 5], "size": "t"}, "25;5": {"type": "stone", "variant": 5, "pos": [25, 5], "size": "t"}, "26;5": {"type": "stone", "variant": 5, "pos": [26, 5], "size": "t"}, "27;5": {"type": "stone", "variant": 5, "pos": [27, 5], "size": "t"}, "28;5": {"type": "stone", "variant": 5, "pos": [28, 5], "size": "t"}, "29;5": {"type": "stone", "variant": 5, "pos": [29, 5], "size": "t"}, "30;5": {"type": "stone", "variant": 5, "pos": [30, 5], "size": "t"}, "31;5": {"type": "stone", "variant": 5, "pos": [31, 5], "size": "t"}, "32;5": {"type": "stone", "variant": 5, "pos": [32, 5], "size": "t"}, "33;5": {"type": "stone", "variant": 5, "pos": [33, 5], "size": "t"}, "34;5": {"type": "stone", "variant": 5, "pos": [34, 5], "size": "t"}, "36;5": {"type": "stone", "variant": 3, "pos": [36, 5], "size": "t"}, "36;6": {"type": "stone", "variant": 3, "pos": [36, 6], "size": "t"}, "36;7": {"type": "stone", "variant": 3, "pos": [36, 7], "size": "t"}, "36;8": {"type": "stone", "variant": 3, "pos": [36, 8], "size": "t"}, "36;9": {"type": "stone", "variant": 3, "pos": [36, 9], "size": "t"}, "36;10": {"type": "stone", "variant": 3, "pos": [36, 10], "size": "t"}, "36;11": {"type": "stone", "variant": 3, "pos": [36, 11], "size": "t"}, "36;12": {"type": "stone", "variant": 3, "pos": [36, 12], "size": "t"}, "36;13": {"type": "stone", "variant": 3, "pos": [36, 13], "size": "t"}, "36;14": {"type": "stone", "variant": 3, "pos": [36, 14], "size": "t"}, "36;16": {"type": "stone", "variant": 3, "pos": [36, 16], "size": "t"}, "36;15": {"type": "stone", "variant": 3, "pos": [36, 15], "size": "t"}, "2;4": {"type": "stone", "variant": 0, "pos": [2, 4], "size": "t"}, "3;4": {"type": "stone", "variant": 1, "pos": [3, 4], "size": "t"}, "4;4": {"type": "stone", "variant": 1, "pos": [4, 4], "size": "t"}, "5;4": {"type": "stone", "variant": 1, "pos": [5, 4], "size": "t"}, "6;4": {"type": "stone", "variant": 1, "pos": [6, 4], "size": "t"}, "7;4": {"type": "stone", "variant": 1, "pos": [7, 4], "size": "t"}, "8;4": {"type": "stone", "variant": 1, "pos": [8, 4], "size": "t"}, "9;4": {"type": "stone", "variant": 1, "pos": [9, 4], "size": "t"}, "10;4": {"type": "stone", "variant": 1, "pos": [10, 4], "size": "t"}, "11;4": {"type": "stone", "variant": 1, "pos": [11, 4], "size": "t"}, "12;4": {"type": "stone", "variant": 1, "pos": [12, 4], "size": "t"}, "13;4": {"type": "stone", "variant": 1, "pos": [13, 4], "size": "t"}, "14;4": {"type": "stone", "variant": 1, "pos": [14, 4], "size": "t"}, "15;4": {"type": "stone", "variant": 1, "pos": [15, 4], "size": "t"}, "16;4": {"type": "stone", "variant": 1, "pos": [16, 4], "size": "t"}, "17;4": {"type": "stone", "variant": 1, "pos": [17, 4], "size": "t"}, "18;4": {"type": "stone", "variant": 1, "pos": [18, 4], "size": "t"}, "19;4": {"type": "stone", "variant": 1, "pos": [19, 4], "size": "t"}, "20;4": {"type": "stone", "variant": 1, "pos": [20, 4], "size": "t"}, "21;4": {"type": "stone", "variant": 1, "pos": [21, 4], "size": "t"}, "22;4": {"type": "stone", "variant": 1, "pos": [22, 4], "size": "t"}, "23;4": {"type": "stone", "variant": 1, "pos": [23, 4], "size": "t"}, "24;4": {"type": "stone", "variant": 1, "pos": [24, 4], "size": "t"}, "25;4": {"type": "stone", "variant": 1, "pos": [25, 4], "size": "t"}, "26;4": {"type": "stone", "variant": 1, "pos": [26, 4], "size": "t"}, "27;4": {"type": "stone", "variant": 1, "pos": [27, 4], "size": "t"}, "28;4": {"type": "stone", "variant": 1, "pos": [28, 4], "size": "t"}, "29;4": {"type": "stone", "variant": 1, "pos": [29, 4], "size": "t"}, "30;4": {"type": "stone", "variant": 1, "pos": [30, 4], "size": "t"}, "31;3": {"type": "stone", "variant": 0, "pos": [31, 3], "size": "t"}, "32;3": {"type": "stone", "variant": 1, "pos": [32, 3], "size": "t"}, "33;3": {"type": "stone", "variant": 2, "pos": [33, 3], "size": "t"}, "33;4": {"type": "stone", "variant": 8, "pos": [33, 4], "size": "t"}, "34;4": {"type": "stone", "variant": 1, "pos": [34, 4], "size": "t"}, "35;4": {"type": "stone", "variant": 1, "pos": [35, 4], "size": "t"}, "36;4": {"type": "stone", "variant": 2, "pos": [36, 4], "size": "t"}, "32;4": {"type": "stone", "variant": 8, "pos": [32, 4], "size": "t"}, "31;4": {"type": "stone", "variant": 8, "pos": [31, 4], "size": "t"}}, "tile_size": 32, "offgrid": {"28.7;3.4": {"type": "large_decor", "variant": 0, "pos": [28.7, 3.4], "size": "a"}, "29.4;5.9": {"type": "large_decor", "variant": 6, "pos": [29.4, 5.9], "size": "a"}, "23.2;19.9": {"type": "large_decor", "variant": 6, "pos": [23.2, 19.9], "size": "a"}, "32.4;5.9": {"type": "large_decor", "variant": 5, "pos": [32.4, 5.9], "size": "a"}, "30.9;6.0": {"type": "large_decor", "variant": 5, "pos": [30.9, 6.0], "size": "a"}, "36.0;18.3": {"type": "large_decor", "variant": 5, "pos": [36.0, 18.3], "size": "a"}, "15.4;15.5": {"type": "large_decor", "variant": 4, "pos": [15.4, 15.5], "size": "a"}, "14.1;0.3": {"type": "large_decor", "variant": 2, "pos": [14.1, 0.3], "size": "a"}, "13.6;13.0": {"type": "large_decor", "variant": 2, "pos": [13.6, 13.0], "size": "a"}, "12.2;13.0": {"type": "large_decor", "variant": 2, "pos": [12.2, 13.0], "size": "a"}, "29.0;12.9": {"type": "large_decor", "variant": 2, "pos": [29.0, 12.9], "size": "a"}, "19.6;16.0": {"type": "large_decor", "variant": 1, "pos": [19.6, 16.0], "size": "a"}, "11.3;16.1": {"type": "large_decor", "variant": 1, "pos": [11.3, 16.1], "size": "a"}, "12.6;16.3": {"type": "large_decor", "variant": 1, "pos": [12.6, 16.3], "size": "a"}, "3.6;16.0": {"type": "large_decor", "variant": 1, "pos": [3.6, 16.0], "size": "a"}, "33.6;16.1": {"type": "large_decor", "variant": 1, "pos": [33.6, 16.1], "size": "a"}, "26.5;6.0": {"type": "large_decor", "variant": 8, "pos": [26.5, 6.0], "size": "a"}, "11.0;5.8": {"type": "large_decor", "variant": 7, "pos": [11.0, 5.8], "size": "a"}, "14.7;5.9": {"type": "large_decor", "variant": 6, "pos": [14.7, 5.9], "size": "a"}, "7.3;6.1": {"type": "large_decor", "variant": 5, "pos": [7.3, 6.1], "size": "a"}, "21.9;16.0": {"type": "decor", "variant": 2, "pos": [21.9, 16.0], "size": "e"}, "20.1;15.4": {"type": "decor", "variant": 2, "pos": [20.1, 15.4], "size": "e"}, "29.5;12.3": {"type": "decor", "variant": 2, "pos": [29.5, 12.3], "size": "e"}, "30.2;12.5": {"type": "decor", "variant": 1, "pos": [30.2, 12.5], "size": "e"}, "33.8;15.5": {"type": "decor", "variant": 1, "pos": [33.8, 15.5], "size": "e"}, "13.0;12.8": {"type": "decor", "variant": 1, "pos": [13.0, 12.8], "size": "e"}, "4.3;15.6": {"type": "decor", "variant": 1, "pos": [4.3, 15.6], "size": "e"}, "8.2;16.0": {"type": "decor", "variant": 0, "pos": [8.2, 16.0], "size": "e"}, "4.7;3.0": {"type": "decor", "variant": 0, "pos": [4.7, 3.0], "size": "e"}, "2.0;3.0": {"type": "decor", "variant": 16, "pos": [2.0, 3.0], "size": "e"}, "27.1;16.0": {"type": "decor", "variant": 13, "pos": [27.1, 16.0], "size": "e"}, "9.7;16.1": {"type": "decor", "variant": 12, "pos": [9.7, 16.1], "size": "e"}, "21.5;5.9": {"type": "decor", "variant": 11, "pos": [21.5, 5.9], "size": "e"}, "23.8;3.6": {"type": "decor", "variant": 10, "pos": [23.8, 3.6], "size": "e"}, "26.0;16.5": {"type": "decor", "variant": 10, "pos": [26.0, 16.5], "size": "e"}, "28.5;16.5": {"type": "decor", "variant": 10, "pos": [28.5, 16.5], "size": "e"}, "29.8;16.5": {"type": "decor", "variant": 10, "pos": [29.8, 16.5], "size": "e"}, "24.4;6.0": {"type": "decor", "variant": 9, "pos": [24.4, 6.0], "size": "e"}, "24.0;5.9": {"type": "decor", "variant": 9, "pos": [24.0, 5.9], "size": "e"}, "21.6;20.0": {"type": "decor", "variant": 9, "pos": [21.6, 20.0], "size": "e"}, "22.8;20.0": {"type": "decor", "variant": 9, "pos": [22.8, 20.0], "size": "e"}, "9.3;20.0": {"type": "decor", "variant": 9, "pos": [9.3, 20.0], "size": "e"}, "6.7;16.4": {"type": "decor", "variant": 8, "pos": [6.7, 16.4], "size": "e"}, "5.6;16.1": {"type": "decor", "variant": 7, "pos": [5.6, 16.1], "size": "e"}, "23.8;16.0": {"type": "decor", "variant": 7, "pos": [23.8, 16.0], "size": "e"}, "22.9;16.1": {"type": "decor", "variant": 6, "pos": [22.9, 16.1], "size": "e"}, "7.5;3.0": {"type": "decor", "variant": 4, "pos": [7.5, 3.0], "size": "e"}, "10.1;3.0": {"type": "decor", "variant": 3, "pos": [10.1, 3.0], "size": "e"}, "20.6;3.0": {"type": "decor", "variant": 2, "pos": [20.6, 3.0], "size": "e"}, "13.6;19.7": {"type": "large_decor", "variant": 8, "pos": [13.6, 19.7], "size": "a"}, "18.7;19.9": {"type": "large_decor", "variant": 8, "pos": [18.7, 19.9], "size": "a"}, "32.9;19.5": {"type": "large_decor", "variant": 8, "pos": [32.9, 19.5], "size": "a"}, "22.5;11.0": {"type": "Boss", "variant": 3, "pos": [22.5, 11.0], "size": "o"}, "6.6;15.0": {"type": "Spawner", "variant": 0, "pos": [6.6, 15.0], "size": "p"}}}